odoo/addons/stock_picking_invoice_link/README.rst
odoo/addons/stock_picking_invoice_link/__init__.py
odoo/addons/stock_picking_invoice_link/__manifest__.py
odoo/addons/stock_picking_invoice_link/i18n/ca.po
odoo/addons/stock_picking_invoice_link/i18n/de.po
odoo/addons/stock_picking_invoice_link/i18n/es.po
odoo/addons/stock_picking_invoice_link/i18n/es_MX.po
odoo/addons/stock_picking_invoice_link/i18n/fi.po
odoo/addons/stock_picking_invoice_link/i18n/fr.po
odoo/addons/stock_picking_invoice_link/i18n/hr.po
odoo/addons/stock_picking_invoice_link/i18n/it.po
odoo/addons/stock_picking_invoice_link/i18n/nl_NL.po
odoo/addons/stock_picking_invoice_link/i18n/pt.po
odoo/addons/stock_picking_invoice_link/i18n/pt_BR.po
odoo/addons/stock_picking_invoice_link/i18n/sl.po
odoo/addons/stock_picking_invoice_link/i18n/stock_picking_invoice_link.pot
odoo/addons/stock_picking_invoice_link/i18n/tr.po
odoo/addons/stock_picking_invoice_link/i18n/tr_TR.po
odoo/addons/stock_picking_invoice_link/models/__init__.py
odoo/addons/stock_picking_invoice_link/models/account_move.py
odoo/addons/stock_picking_invoice_link/models/stock_move.py
odoo/addons/stock_picking_invoice_link/models/stock_picking.py
odoo/addons/stock_picking_invoice_link/readme/CONTRIBUTORS.md
odoo/addons/stock_picking_invoice_link/readme/CREDITS.md
odoo/addons/stock_picking_invoice_link/readme/DESCRIPTION.md
odoo/addons/stock_picking_invoice_link/readme/USAGE.md
odoo/addons/stock_picking_invoice_link/static/description/icon.png
odoo/addons/stock_picking_invoice_link/static/description/index.html
odoo/addons/stock_picking_invoice_link/tests/__init__.py
odoo/addons/stock_picking_invoice_link/tests/test_stock_picking_invoice_link.py
odoo/addons/stock_picking_invoice_link/views/account_invoice_view.xml
odoo/addons/stock_picking_invoice_link/views/stock_view.xml
odoo/addons/stock_picking_invoice_link/wizards/__init__.py
odoo/addons/stock_picking_invoice_link/wizards/account_move_reversal.py
odoo_addon_stock_picking_invoice_link-19.0.1.0.0.2.dist-info/METADATA
odoo_addon_stock_picking_invoice_link-19.0.1.0.0.2.dist-info/WHEEL
odoo_addon_stock_picking_invoice_link-19.0.1.0.0.2.dist-info/top_level.txt
odoo_addon_stock_picking_invoice_link-19.0.1.0.0.2.dist-info/RECORD
