Metadata-Version: 2.1
Name: odoo-addon-stock_picking_invoice_link
Version: 19.0.1.0.0.2
Requires-Dist: odoo==19.0.*
Summary: Adds link between pickings and invoices
Home-page: https://github.com/OCA/stock-logistics-workflow
License: AGPL-3
Author: Agile Business Group, Tecnativa, BCIM sprl, Softdil S.L, Odoo Community Association (OCA)
Author-email: support@odoo-community.org
Classifier: Programming Language :: Python
Classifier: Framework :: Odoo
Classifier: Framework :: Odoo :: 19.0
Classifier: License :: OSI Approved :: GNU Affero General Public License v3
Classifier: Development Status :: 6 - Mature
